hyperscore/__init__.py
hyperscore/core/__init__.py
hyperscore/core/score.py
hyperscore/core/time.py
hyperscore/core/time_pipeline.py
hyperscore/core/time_transforms.py
hyperscore/io/__init__.py
hyperscore/io/midi.py
hyperscore/py.typed
hyperscore/rhythm/__init__.py
hyperscore/rhythm/rhythm_tree.py
hyperscore/theory/__init__.py
hyperscore/theory/pcset.py
hyperscore/theory/scales.py
hyperscore-0.2.0.dist-info/WHEEL
hyperscore-0.2.0.dist-info/METADATA
hyperscore-0.2.0.dist-info/RECORD
