Metadata-Version: 2.3
Name: hyperscore
Version: 0.2.0
Summary: Structural music composition framework
Author: inaba1115
Author-email: inaba1115 <inaba1115@gmail.com>
Classifier: Programming Language :: Python :: 3 :: Only
Classifier: Programming Language :: Python :: 3.10
Classifier: Topic :: Multimedia :: Sound/Audio
Classifier: Topic :: Scientific/Engineering
Requires-Dist: lark>=1.3.1
Requires-Dist: mido>=1.3.3
Requires-Dist: python-rtmidi>=1.5.8
Requires-Python: >=3.10
